interpret_vision/__init__.py
interpret_vision/text_explainer.py
interpret_vision/common/__init__.py
interpret_vision/common/structured_model_mixin.py
interpret_vision/common/text_explainer_utils.py
interpret_vision/explanation/__init__.py
interpret_vision/explanation/explanation.py
interpret_vision-0.1.0.0.dist-info/LICENSE
interpret_vision-0.1.0.0.dist-info/METADATA
interpret_vision-0.1.0.0.dist-info/WHEEL
interpret_vision-0.1.0.0.dist-info/top_level.txt
interpret_vision-0.1.0.0.dist-info/RECORD
